<?xml version="1.0" encoding="utf-8"?>
<!-- edited with XMLSPY v2004 rel. 2 U (http://www.xmlspy.com) by Ed Beach (Firaxis Games) -->
<!-- Sid Meier's Civilization 5 -->
<!-- Copyright Firaxis Games 2010 -->
<!-- AI Military Strategy Infos -->
<!-- -->
<!-- Entries in this file define the attributes of various AI Player Strategies.  Entries can be completely removed safely, but be careful when changing values, as this can result in unexpected AI behavior.  Defines which also help shape use of AI Player Strategies are located in the GlobalAIDefines.xml file inside the XML\AI\ directory.  Flavors determine which Units, Buildings, Techs, Policies, etc. a Player wants to obtain.  WeightThreshold is used in the AI code to determine if this Strategy should be adopted - note that it's used in a different way by each Strategy.  PersonalityFlavorThresholdMods change the liklihood of a Strategy being adopted based on the AI player's intrinsic Flavors.  As with WeightThreshold, the use of the PersonalityFlavorMod values isn't consistent across all Strategies.  For more information on how these Strategies work, reference CvMilitaryAI.cpp in the GameCoreDLL project.-->
<!-- -->
<GameData>
	<!-- Table definition -->
	<Table name="AIMilitaryStrategies">
		<Column name="ID" type="integer" primarykey="true" autoincrement="true"/>
		<Column name="Type" type="text" notnull="true" unique="true"/>
		<Column name="DontUpdateCityFlavors" type="boolean" default="false"/>
		<Column name="NoMinorCivs" type="boolean" default="false"/>
		<Column name="OnlyMinorCivs" type="boolean" default="false"/>
		<Column name="UpdateCitySpecializations" type="boolean" default="false"/>
		<Column name="CheckTriggerTurnCount" type="integer" default="0"/>
		<Column name="FirstTurnExecuted" type="integer" default="0"/>
		<Column name="MinimumNumTurnsExecuted" type="integer" default="0"/>
		<Column name="WeightThreshold" type="integer" default="0"/>
		<Column name="TechObsolete" type="text" reference="Technologies(Type)" default="NULL"/>
		<Column name="TechPrereq" type="text" reference="Technologies(Type)" default="NULL"/>
		<Column name="Advisor" type="text"/>
		<Column name="AdvisorCounsel" type="text"/>
		<Column name="AdvisorCounselImportance" type="integer" default="1"/>
	</Table>
	<Table name="AIMilitaryStrategy_Flavors">
		<Column name="AIMilitaryStrategyType" type="text" reference="AIMilitaryStrategies(Type)"/>
		<Column name="FlavorType" type="text" reference="Flavors(Type)"/>
		<Column name="Flavor" type="integer"/>
	</Table>
	<Table name="AIMilitaryStrategy_PersonalityFlavorThresholdMods">
		<Column name="AIMilitaryStrategyType" type="text" reference="AIMilitaryStrategies(Type)"/>
		<Column name="FlavorType" type="text" reference="Flavors(Type)"/>
		<Column name="Flavor" type="integer"/>
	</Table>
	<AIMilitaryStrategies>
		<Row>
			<ID>0</ID>
			<Type>MILITARYAISTRATEGY_NEED_RANGED</Type>
			<CheckTriggerTurnCount>2</CheckTriggerTurnCount>
			<MinimumNumTurnsExecuted>2</MinimumNumTurnsExecuted>
			<FirstTurnExecuted>25</FirstTurnExecuted>
		</Row>
		<Row>
			<Type>MILITARYAISTRATEGY_ENOUGH_MILITARY_UNITS</Type>
			<CheckTriggerTurnCount>2</CheckTriggerTurnCount>
			<MinimumNumTurnsExecuted>2</MinimumNumTurnsExecuted>
			<FirstTurnExecuted>25</FirstTurnExecuted>
			<NoMinorCivs>true</NoMinorCivs>
			<Advisor>ECONOMIC</Advisor>
			<AdvisorCounsel>TXT_KEY_MILITARYAISTRATEGY_ENOUGH_MILITARY_UNITS</AdvisorCounsel>
			<AdvisorCounselImportance>1</AdvisorCounselImportance>
		</Row>
		<Row>
			<Type>MILITARYAISTRATEGY_EMPIRE_DEFENSE</Type>
			<CheckTriggerTurnCount>2</CheckTriggerTurnCount>
			<MinimumNumTurnsExecuted>5</MinimumNumTurnsExecuted>
			<FirstTurnExecuted>25</FirstTurnExecuted>
			<NoMinorCivs>true</NoMinorCivs>
			<UpdateCitySpecializations>true</UpdateCitySpecializations>
			<Advisor>MILITARY</Advisor>
			<AdvisorCounsel>TXT_KEY_MILITARYAISTRATEGY_EMPIRE_DEFENSE</AdvisorCounsel>
			<AdvisorCounselImportance>1</AdvisorCounselImportance>
		</Row>
		<Row>
			<Type>MILITARYAISTRATEGY_EMPIRE_DEFENSE_CRITICAL</Type>
			<CheckTriggerTurnCount>2</CheckTriggerTurnCount>
			<MinimumNumTurnsExecuted>5</MinimumNumTurnsExecuted>
			<FirstTurnExecuted>30</FirstTurnExecuted>
			<!--<NoMinorCivs>true</NoMinorCivs>-->
			<UpdateCitySpecializations>true</UpdateCitySpecializations>
			<Advisor>MILITARY</Advisor>
			<AdvisorCounsel>TXT_KEY_MILITARYAISTRATEGY_EMPIRE_DEFENSE_CRITICAL</AdvisorCounsel>
			<AdvisorCounselImportance>3</AdvisorCounselImportance>
		</Row>
		<Row>
			<Type>MILITARYAISTRATEGY_ENOUGH_NAVAL_UNITS</Type>
			<CheckTriggerTurnCount>2</CheckTriggerTurnCount>
			<MinimumNumTurnsExecuted>2</MinimumNumTurnsExecuted>
			<FirstTurnExecuted>50</FirstTurnExecuted>
			<NoMinorCivs>true</NoMinorCivs>
		</Row>
		<Row>
			<Type>MILITARYAISTRATEGY_NEED_NAVAL_UNITS</Type>
			<CheckTriggerTurnCount>2</CheckTriggerTurnCount>
			<MinimumNumTurnsExecuted>2</MinimumNumTurnsExecuted>
			<FirstTurnExecuted>50</FirstTurnExecuted>
			<NoMinorCivs>true</NoMinorCivs>
		</Row>
		<Row>
			<Type>MILITARYAISTRATEGY_NEED_NAVAL_UNITS_CRITICAL</Type>
			<CheckTriggerTurnCount>2</CheckTriggerTurnCount>
			<MinimumNumTurnsExecuted>2</MinimumNumTurnsExecuted>
			<FirstTurnExecuted>50</FirstTurnExecuted>
			<NoMinorCivs>true</NoMinorCivs>
			<UpdateCitySpecializations>true</UpdateCitySpecializations>
		</Row>
		<Row>
			<Type>MILITARYAISTRATEGY_AT_WAR</Type>
			<CheckTriggerTurnCount>1</CheckTriggerTurnCount>
			<MinimumNumTurnsExecuted>5</MinimumNumTurnsExecuted>
			<NoMinorCivs>true</NoMinorCivs>
			<UpdateCitySpecializations>true</UpdateCitySpecializations>
			<Advisor>MILITARY</Advisor>
			<AdvisorCounsel>TXT_KEY_MILITARYAISTRATEGY_AT_WAR</AdvisorCounsel>
			<AdvisorCounselImportance>1</AdvisorCounselImportance>
		</Row>
		<Row>
			<Type>MILITARYAISTRATEGY_WAR_MOBILIZATION</Type>
			<CheckTriggerTurnCount>5</CheckTriggerTurnCount>
			<MinimumNumTurnsExecuted>15</MinimumNumTurnsExecuted>
			<WeightThreshold>100</WeightThreshold>
			<NoMinorCivs>true</NoMinorCivs>
			<UpdateCitySpecializations>true</UpdateCitySpecializations>
		</Row>
		<Row>
			<Type>MILITARYAISTRATEGY_NEED_RANGED_EARLY</Type>
			<CheckTriggerTurnCount>5</CheckTriggerTurnCount>
			<NoMinorCivs>true</NoMinorCivs>
			<TechObsolete>TECH_ARCHERY</TechObsolete>
			<UpdateCitySpecializations>true</UpdateCitySpecializations>
		</Row>
		<Row>
			<Type>MILITARYAISTRATEGY_ENOUGH_RANGED</Type>
			<CheckTriggerTurnCount>2</CheckTriggerTurnCount>
			<MinimumNumTurnsExecuted>2</MinimumNumTurnsExecuted>
			<FirstTurnExecuted>25</FirstTurnExecuted>
		</Row>
		<Row>
			<Type>MILITARYAISTRATEGY_MINOR_CIV_GENERAL_DEFENSE</Type>
			<CheckTriggerTurnCount>50</CheckTriggerTurnCount>
			<MinimumNumTurnsExecuted>50</MinimumNumTurnsExecuted>
			<OnlyMinorCivs>true</OnlyMinorCivs>
		</Row>
		<Row>
			<Type>MILITARYAISTRATEGY_MINOR_CIV_THREAT_ELEVATED</Type>
			<CheckTriggerTurnCount>5</CheckTriggerTurnCount>
			<MinimumNumTurnsExecuted>5</MinimumNumTurnsExecuted>
			<OnlyMinorCivs>true</OnlyMinorCivs>
		</Row>
		<Row>
			<Type>MILITARYAISTRATEGY_MINOR_CIV_THREAT_CRITICAL</Type>
			<CheckTriggerTurnCount>5</CheckTriggerTurnCount>
			<MinimumNumTurnsExecuted>5</MinimumNumTurnsExecuted>
			<OnlyMinorCivs>true</OnlyMinorCivs>
		</Row>
		<Row>
			<Type>MILITARYAISTRATEGY_ERADICATE_BARBARIANS</Type>
			<CheckTriggerTurnCount>5</CheckTriggerTurnCount>
			<MinimumNumTurnsExecuted>5</MinimumNumTurnsExecuted>
			<FirstTurnExecuted>25</FirstTurnExecuted>
			<NoMinorCivs>true</NoMinorCivs>
			<WeightThreshold>75</WeightThreshold>
			<Advisor>MILITARY</Advisor>
			<AdvisorCounsel>TXT_KEY_MILITARYAISTRATEGY_ERADICATE_BARBARIANS</AdvisorCounsel>
			<AdvisorCounselImportance>1</AdvisorCounselImportance>
		</Row>
		<Row>
			<Type>MILITARYAISTRATEGY_WINNING_WARS</Type>
			<CheckTriggerTurnCount>2</CheckTriggerTurnCount>
			<MinimumNumTurnsExecuted>2</MinimumNumTurnsExecuted>
			<NoMinorCivs>true</NoMinorCivs>
			<Advisor>MILITARY</Advisor>
			<AdvisorCounsel>TXT_KEY_MILITARYAISTRATEGY_WINNING_WARS</AdvisorCounsel>
			<AdvisorCounselImportance>1</AdvisorCounselImportance>
		</Row>
		<Row>
			<Type>MILITARYAISTRATEGY_LOSING_WARS</Type>
			<CheckTriggerTurnCount>2</CheckTriggerTurnCount>
			<MinimumNumTurnsExecuted>2</MinimumNumTurnsExecuted>
			<NoMinorCivs>true</NoMinorCivs>
			<Advisor>FOREIGN</Advisor>
			<AdvisorCounsel>TXT_KEY_MILITARYAISTRATEGY_LOSING_WARS</AdvisorCounsel>
			<AdvisorCounselImportance>1</AdvisorCounselImportance>
		</Row>
		<Row>
			<Type>MILITARYAISTRATEGY_NEED_MOBILE</Type>
			<CheckTriggerTurnCount>2</CheckTriggerTurnCount>
			<MinimumNumTurnsExecuted>2</MinimumNumTurnsExecuted>
			<FirstTurnExecuted>25</FirstTurnExecuted>
			<!-- <TechObsolete>TECH_COMBUSTION</TechObsolete> -->
		</Row>
		<Row>
			<Type>MILITARYAISTRATEGY_ENOUGH_MOBILE</Type>
			<CheckTriggerTurnCount>2</CheckTriggerTurnCount>
			<MinimumNumTurnsExecuted>2</MinimumNumTurnsExecuted>
			<FirstTurnExecuted>25</FirstTurnExecuted>
			<!-- <TechObsolete>TECH_COMBUSTION</TechObsolete> -->
		</Row>
		<Row>
			<Type>MILITARYAISTRATEGY_NEED_AIR</Type>
			<CheckTriggerTurnCount>2</CheckTriggerTurnCount>
			<MinimumNumTurnsExecuted>2</MinimumNumTurnsExecuted>
			<NoMinorCivs>true</NoMinorCivs>
			<FirstTurnExecuted>25</FirstTurnExecuted>
			<TechPrereq>TECH_FLIGHT</TechPrereq>
		</Row>
		<Row>
			<Type>MILITARYAISTRATEGY_NEED_NUKE</Type>
			<CheckTriggerTurnCount>2</CheckTriggerTurnCount>
			<MinimumNumTurnsExecuted>2</MinimumNumTurnsExecuted>
			<NoMinorCivs>true</NoMinorCivs>
			<FirstTurnExecuted>25</FirstTurnExecuted>
			<TechPrereq>TECH_ATOMIC_THEORY</TechPrereq>
		</Row>
		<Row>
			<Type>MILITARYAISTRATEGY_ENOUGH_AIR</Type>
			<CheckTriggerTurnCount>2</CheckTriggerTurnCount>
			<MinimumNumTurnsExecuted>2</MinimumNumTurnsExecuted>
			<NoMinorCivs>true</NoMinorCivs>
			<FirstTurnExecuted>25</FirstTurnExecuted>
			<TechPrereq>TECH_FLIGHT</TechPrereq>
		</Row>
		<Row>
			<Type>MILITARYAISTRATEGY_NEED_ANTIAIR</Type>
			<CheckTriggerTurnCount>2</CheckTriggerTurnCount>
			<MinimumNumTurnsExecuted>2</MinimumNumTurnsExecuted>
			<FirstTurnExecuted>25</FirstTurnExecuted>
			<TechPrereq>TECH_RADIO</TechPrereq>
		</Row>
		<Row>
			<Type>MILITARYAISTRATEGY_ENOUGH_ANTIAIR</Type>
			<CheckTriggerTurnCount>2</CheckTriggerTurnCount>
			<MinimumNumTurnsExecuted>2</MinimumNumTurnsExecuted>
			<FirstTurnExecuted>25</FirstTurnExecuted>
			<TechPrereq>TECH_RADIO</TechPrereq>
		</Row>
	</AIMilitaryStrategies>
	<AIMilitaryStrategy_Flavors>
		<Row>
			<AIMilitaryStrategyType>MILITARYAISTRATEGY_ENOUGH_MILITARY_UNITS</AIMilitaryStrategyType>
			<FlavorType>FLAVOR_OFFENSE</FlavorType>
			<Flavor>-100</Flavor>
		</Row>
		<Row>
			<AIMilitaryStrategyType>MILITARYAISTRATEGY_ENOUGH_MILITARY_UNITS</AIMilitaryStrategyType>
			<FlavorType>FLAVOR_DEFENSE</FlavorType>
			<Flavor>-100</Flavor>
		</Row>
		<Row>
			<AIMilitaryStrategyType>MILITARYAISTRATEGY_EMPIRE_DEFENSE</AIMilitaryStrategyType>
			<FlavorType>FLAVOR_OFFENSE</FlavorType>
			<Flavor>10</Flavor>
		</Row>
		<Row>
			<AIMilitaryStrategyType>MILITARYAISTRATEGY_EMPIRE_DEFENSE</AIMilitaryStrategyType>
			<FlavorType>FLAVOR_DEFENSE</FlavorType>
			<Flavor>25</Flavor>
		</Row>
		<Row>
			<AIMilitaryStrategyType>MILITARYAISTRATEGY_EMPIRE_DEFENSE</AIMilitaryStrategyType>
			<FlavorType>FLAVOR_CITY_DEFENSE</FlavorType>
			<Flavor>10</Flavor>
		</Row>
		<Row>
			<AIMilitaryStrategyType>MILITARYAISTRATEGY_EMPIRE_DEFENSE</AIMilitaryStrategyType>
			<FlavorType>FLAVOR_MILITARY_TRAINING</FlavorType>
			<Flavor>10</Flavor>
		</Row>
		<Row>
			<AIMilitaryStrategyType>MILITARYAISTRATEGY_EMPIRE_DEFENSE</AIMilitaryStrategyType>
			<FlavorType>FLAVOR_EXPANSION</FlavorType>
			<Flavor>-10</Flavor>
		</Row>
		<Row>
			<AIMilitaryStrategyType>MILITARYAISTRATEGY_EMPIRE_DEFENSE</AIMilitaryStrategyType>
			<FlavorType>FLAVOR_TILE_IMPROVEMENT</FlavorType>
			<Flavor>-5</Flavor>
		</Row>
		<Row>
			<AIMilitaryStrategyType>MILITARYAISTRATEGY_EMPIRE_DEFENSE_CRITICAL</AIMilitaryStrategyType>
			<FlavorType>FLAVOR_OFFENSE</FlavorType>
			<Flavor>15</Flavor>
		</Row>
		<Row>
			<AIMilitaryStrategyType>MILITARYAISTRATEGY_EMPIRE_DEFENSE_CRITICAL</AIMilitaryStrategyType>
			<FlavorType>FLAVOR_DEFENSE</FlavorType>
			<Flavor>60</Flavor>
		</Row>
		<Row>
			<AIMilitaryStrategyType>MILITARYAISTRATEGY_EMPIRE_DEFENSE_CRITICAL</AIMilitaryStrategyType>
			<FlavorType>FLAVOR_NAVAL</FlavorType>
			<Flavor>-10</Flavor>
		</Row>
		<Row>
			<AIMilitaryStrategyType>MILITARYAISTRATEGY_EMPIRE_DEFENSE_CRITICAL</AIMilitaryStrategyType>
			<FlavorType>FLAVOR_NAVAL_RECON</FlavorType>
			<Flavor>-10</Flavor>
		</Row>
		<Row>
			<AIMilitaryStrategyType>MILITARYAISTRATEGY_EMPIRE_DEFENSE_CRITICAL</AIMilitaryStrategyType>
			<FlavorType>FLAVOR_RECON</FlavorType>
			<Flavor>-20</Flavor>
		</Row>
		<Row>
			<AIMilitaryStrategyType>MILITARYAISTRATEGY_EMPIRE_DEFENSE_CRITICAL</AIMilitaryStrategyType>
			<FlavorType>FLAVOR_EXPANSION</FlavorType>
			<Flavor>-20</Flavor>
		</Row>
		<Row>
			<AIMilitaryStrategyType>MILITARYAISTRATEGY_EMPIRE_DEFENSE_CRITICAL</AIMilitaryStrategyType>
			<FlavorType>FLAVOR_TILE_IMPROVEMENT</FlavorType>
			<Flavor>-20</Flavor>
		</Row>
		<Row>
			<AIMilitaryStrategyType>MILITARYAISTRATEGY_EMPIRE_DEFENSE_CRITICAL</AIMilitaryStrategyType>
			<FlavorType>FLAVOR_INFRASTRUCTURE</FlavorType>
			<Flavor>-20</Flavor>
		</Row>
		<Row>
			<AIMilitaryStrategyType>MILITARYAISTRATEGY_EMPIRE_DEFENSE_CRITICAL</AIMilitaryStrategyType>
			<FlavorType>FLAVOR_CULTURE</FlavorType>
			<Flavor>-20</Flavor>
		</Row>
		<Row>
			<AIMilitaryStrategyType>MILITARYAISTRATEGY_EMPIRE_DEFENSE_CRITICAL</AIMilitaryStrategyType>
			<FlavorType>FLAVOR_WONDER</FlavorType>
			<Flavor>-20</Flavor>
		</Row>
		<Row>
			<AIMilitaryStrategyType>MILITARYAISTRATEGY_ENOUGH_NAVAL_UNITS</AIMilitaryStrategyType>
			<FlavorType>FLAVOR_NAVAL</FlavorType>
			<Flavor>-100</Flavor>
		</Row>
		<Row>
			<AIMilitaryStrategyType>MILITARYAISTRATEGY_ENOUGH_NAVAL_UNITS</AIMilitaryStrategyType>
			<FlavorType>FLAVOR_NAVAL_RECON</FlavorType>
			<Flavor>-100</Flavor>
		</Row>
		<Row>
			<AIMilitaryStrategyType>MILITARYAISTRATEGY_NEED_NAVAL_UNITS</AIMilitaryStrategyType>
			<FlavorType>FLAVOR_NAVAL</FlavorType>
			<Flavor>40</Flavor>
		</Row>
		<Row>
			<AIMilitaryStrategyType>MILITARYAISTRATEGY_NEED_NAVAL_UNITS</AIMilitaryStrategyType>
			<FlavorType>FLAVOR_NAVAL_RECON</FlavorType>
			<Flavor>10</Flavor>
		</Row>
		<Row>
			<AIMilitaryStrategyType>MILITARYAISTRATEGY_NEED_NAVAL_UNITS</AIMilitaryStrategyType>
			<FlavorType>FLAVOR_OFFENSE</FlavorType>
			<Flavor>-10</Flavor>
		</Row>
		<Row>
			<AIMilitaryStrategyType>MILITARYAISTRATEGY_NEED_NAVAL_UNITS</AIMilitaryStrategyType>
			<FlavorType>FLAVOR_DEFENSE</FlavorType>
			<Flavor>-10</Flavor>
		</Row>
		<Row>
			<AIMilitaryStrategyType>MILITARYAISTRATEGY_NEED_NAVAL_UNITS_CRITICAL</AIMilitaryStrategyType>
			<FlavorType>FLAVOR_NAVAL</FlavorType>
			<Flavor>70</Flavor>
		</Row>
		<Row>
			<AIMilitaryStrategyType>MILITARYAISTRATEGY_NEED_NAVAL_UNITS_CRITICAL</AIMilitaryStrategyType>
			<FlavorType>FLAVOR_NAVAL_RECON</FlavorType>
			<Flavor>25</Flavor>
		</Row>
		<Row>
			<AIMilitaryStrategyType>MILITARYAISTRATEGY_NEED_NAVAL_UNITS_CRITICAL</AIMilitaryStrategyType>
			<FlavorType>FLAVOR_OFFENSE</FlavorType>
			<Flavor>-20</Flavor>
		</Row>
		<Row>
			<AIMilitaryStrategyType>MILITARYAISTRATEGY_NEED_NAVAL_UNITS_CRITICAL</AIMilitaryStrategyType>
			<FlavorType>FLAVOR_DEFENSE</FlavorType>
			<Flavor>-20</Flavor>
		</Row>
		<Row>
			<AIMilitaryStrategyType>MILITARYAISTRATEGY_AT_WAR</AIMilitaryStrategyType>
			<FlavorType>FLAVOR_OFFENSE</FlavorType>
			<Flavor>15</Flavor>
		</Row>
		<Row>
			<AIMilitaryStrategyType>MILITARYAISTRATEGY_AT_WAR</AIMilitaryStrategyType>
			<FlavorType>FLAVOR_MOBILE</FlavorType>
			<Flavor>15</Flavor>
		</Row>
		<Row>
			<AIMilitaryStrategyType>MILITARYAISTRATEGY_AT_WAR</AIMilitaryStrategyType>
			<FlavorType>FLAVOR_DEFENSE</FlavorType>
			<Flavor>15</Flavor>
		</Row>
		<Row>
			<AIMilitaryStrategyType>MILITARYAISTRATEGY_AT_WAR</AIMilitaryStrategyType>
			<FlavorType>FLAVOR_RANGED</FlavorType>
			<Flavor>15</Flavor>
		</Row>
		<Row>
			<AIMilitaryStrategyType>MILITARYAISTRATEGY_AT_WAR</AIMilitaryStrategyType>
			<FlavorType>FLAVOR_NAVAL</FlavorType>
			<Flavor>15</Flavor>
		</Row>
		<Row>
			<AIMilitaryStrategyType>MILITARYAISTRATEGY_AT_WAR</AIMilitaryStrategyType>
			<FlavorType>FLAVOR_AIR</FlavorType>
			<Flavor>20</Flavor>
		</Row>
		<Row>
			<AIMilitaryStrategyType>MILITARYAISTRATEGY_AT_WAR</AIMilitaryStrategyType>
			<FlavorType>FLAVOR_CITY_DEFENSE</FlavorType>
			<Flavor>20</Flavor>
		</Row>
		<Row>
			<AIMilitaryStrategyType>MILITARYAISTRATEGY_AT_WAR</AIMilitaryStrategyType>
			<FlavorType>FLAVOR_WONDER</FlavorType>
			<Flavor>-10</Flavor>
		</Row>
		<Row>
			<AIMilitaryStrategyType>MILITARYAISTRATEGY_AT_WAR</AIMilitaryStrategyType>
			<FlavorType>FLAVOR_EXPANSION</FlavorType>
			<Flavor>-20</Flavor>
		</Row>
		<Row>
			<AIMilitaryStrategyType>MILITARYAISTRATEGY_WAR_MOBILIZATION</AIMilitaryStrategyType>
			<FlavorType>FLAVOR_OFFENSE</FlavorType>
			<Flavor>15</Flavor>
		</Row>
		<Row>
			<AIMilitaryStrategyType>MILITARYAISTRATEGY_WAR_MOBILIZATION</AIMilitaryStrategyType>
			<FlavorType>FLAVOR_DEFENSE</FlavorType>
			<Flavor>10</Flavor>
		</Row>
		<Row>
			<AIMilitaryStrategyType>MILITARYAISTRATEGY_WAR_MOBILIZATION</AIMilitaryStrategyType>
			<FlavorType>FLAVOR_RANGED</FlavorType>
			<Flavor>10</Flavor>
		</Row>
		<Row>
			<AIMilitaryStrategyType>MILITARYAISTRATEGY_WAR_MOBILIZATION</AIMilitaryStrategyType>
			<FlavorType>FLAVOR_MOBILE</FlavorType>
			<Flavor>10</Flavor>
		</Row>
		<Row>
			<AIMilitaryStrategyType>MILITARYAISTRATEGY_WAR_MOBILIZATION</AIMilitaryStrategyType>
			<FlavorType>FLAVOR_NAVAL</FlavorType>
			<Flavor>10</Flavor>
		</Row>
		<Row>
			<AIMilitaryStrategyType>MILITARYAISTRATEGY_WAR_MOBILIZATION</AIMilitaryStrategyType>
			<FlavorType>FLAVOR_MILITARY_TRAINING</FlavorType>
			<Flavor>25</Flavor>
		</Row>
		<Row>
			<AIMilitaryStrategyType>MILITARYAISTRATEGY_WAR_MOBILIZATION</AIMilitaryStrategyType>
			<FlavorType>FLAVOR_WONDER</FlavorType>
			<Flavor>-250</Flavor>
		</Row>
		<Row>
			<AIMilitaryStrategyType>MILITARYAISTRATEGY_WAR_MOBILIZATION</AIMilitaryStrategyType>
			<FlavorType>FLAVOR_GROWTH</FlavorType>
			<Flavor>-50</Flavor>
		</Row>
		<Row>
			<AIMilitaryStrategyType>MILITARYAISTRATEGY_WAR_MOBILIZATION</AIMilitaryStrategyType>
			<FlavorType>FLAVOR_EXPANSION</FlavorType>
			<Flavor>-50</Flavor>
		</Row>
		<Row>
			<AIMilitaryStrategyType>MILITARYAISTRATEGY_WAR_MOBILIZATION</AIMilitaryStrategyType>
			<FlavorType>FLAVOR_TILE_IMPROVEMENT</FlavorType>
			<Flavor>-50</Flavor>
		</Row>
		<Row>
			<AIMilitaryStrategyType>MILITARYAISTRATEGY_WAR_MOBILIZATION</AIMilitaryStrategyType>
			<FlavorType>FLAVOR_CULTURE</FlavorType>
			<Flavor>-50</Flavor>
		</Row>
		<Row>
			<AIMilitaryStrategyType>MILITARYAISTRATEGY_NEED_RANGED_EARLY</AIMilitaryStrategyType>
			<FlavorType>FLAVOR_RANGED</FlavorType>
			<Flavor>100</Flavor>
		</Row>
		<Row>
			<AIMilitaryStrategyType>MILITARYAISTRATEGY_MINOR_CIV_GENERAL_DEFENSE</AIMilitaryStrategyType>
			<FlavorType>FLAVOR_DEFENSE</FlavorType>
			<Flavor>6</Flavor>
		</Row>
		<Row>
			<AIMilitaryStrategyType>MILITARYAISTRATEGY_MINOR_CIV_GENERAL_DEFENSE</AIMilitaryStrategyType>
			<FlavorType>FLAVOR_CITY_DEFENSE</FlavorType>
			<Flavor>10</Flavor>
		</Row>
		<Row>
			<AIMilitaryStrategyType>MILITARYAISTRATEGY_MINOR_CIV_THREAT_ELEVATED</AIMilitaryStrategyType>
			<FlavorType>FLAVOR_DEFENSE</FlavorType>
			<Flavor>10</Flavor>
		</Row>
		<Row>
			<AIMilitaryStrategyType>MILITARYAISTRATEGY_MINOR_CIV_THREAT_ELEVATED</AIMilitaryStrategyType>
			<FlavorType>FLAVOR_CITY_DEFENSE</FlavorType>
			<Flavor>20</Flavor>
		</Row>
		<Row>
			<AIMilitaryStrategyType>MILITARYAISTRATEGY_MINOR_CIV_THREAT_CRITICAL</AIMilitaryStrategyType>
			<FlavorType>FLAVOR_OFFENSE</FlavorType>
			<Flavor>20</Flavor>
		</Row>
		<Row>
			<AIMilitaryStrategyType>MILITARYAISTRATEGY_MINOR_CIV_THREAT_CRITICAL</AIMilitaryStrategyType>
			<FlavorType>FLAVOR_DEFENSE</FlavorType>
			<Flavor>20</Flavor>
		</Row>
		<Row>
			<AIMilitaryStrategyType>MILITARYAISTRATEGY_MINOR_CIV_THREAT_CRITICAL</AIMilitaryStrategyType>
			<FlavorType>FLAVOR_CITY_DEFENSE</FlavorType>
			<Flavor>40</Flavor>
		</Row>
		<Row>
			<AIMilitaryStrategyType>MILITARYAISTRATEGY_ERADICATE_BARBARIANS</AIMilitaryStrategyType>
			<FlavorType>FLAVOR_OFFENSE</FlavorType>
			<Flavor>10</Flavor>
		</Row>
		<Row>
			<AIMilitaryStrategyType>MILITARYAISTRATEGY_ERADICATE_BARBARIANS</AIMilitaryStrategyType>
			<FlavorType>FLAVOR_MOBILE</FlavorType>
			<Flavor>10</Flavor>
		</Row>
		<Row>
			<AIMilitaryStrategyType>MILITARYAISTRATEGY_ERADICATE_BARBARIANS</AIMilitaryStrategyType>
			<FlavorType>FLAVOR_RANGED</FlavorType>
			<Flavor>5</Flavor>
		</Row>
		<Row>
			<AIMilitaryStrategyType>MILITARYAISTRATEGY_WINNING_WARS</AIMilitaryStrategyType>
			<FlavorType>FLAVOR_OFFENSE</FlavorType>
			<Flavor>5</Flavor>
		</Row>
		<Row>
			<AIMilitaryStrategyType>MILITARYAISTRATEGY_WINNING_WARS</AIMilitaryStrategyType>
			<FlavorType>FLAVOR_DEFENSE</FlavorType>
			<Flavor>-5</Flavor>
		</Row>
		<Row>
			<AIMilitaryStrategyType>MILITARYAISTRATEGY_LOSING_WARS</AIMilitaryStrategyType>
			<FlavorType>FLAVOR_OFFENSE</FlavorType>
			<Flavor>-5</Flavor>
		</Row>
		<Row>
			<AIMilitaryStrategyType>MILITARYAISTRATEGY_LOSING_WARS</AIMilitaryStrategyType>
			<FlavorType>FLAVOR_DEFENSE</FlavorType>
			<Flavor>5</Flavor>
		</Row>
		<Row>
			<AIMilitaryStrategyType>MILITARYAISTRATEGY_LOSING_WARS</AIMilitaryStrategyType>
			<FlavorType>FLAVOR_CITY_DEFENSE</FlavorType>
			<Flavor>25</Flavor>
		</Row>
		<Row>
			<AIMilitaryStrategyType>MILITARYAISTRATEGY_LOSING_WARS</AIMilitaryStrategyType>
			<FlavorType>FLAVOR_EXPANSION</FlavorType>
			<Flavor>-50</Flavor>
		</Row>
		<Row>
			<AIMilitaryStrategyType>MILITARYAISTRATEGY_LOSING_WARS</AIMilitaryStrategyType>
			<FlavorType>FLAVOR_TILE_IMPROVEMENT</FlavorType>
			<Flavor>-25</Flavor>
		</Row>
		<Row>
			<AIMilitaryStrategyType>MILITARYAISTRATEGY_LOSING_WARS</AIMilitaryStrategyType>
			<FlavorType>FLAVOR_RECON</FlavorType>
			<Flavor>-15</Flavor>
		</Row>
		<Row>
			<AIMilitaryStrategyType>MILITARYAISTRATEGY_LOSING_WARS</AIMilitaryStrategyType>
			<FlavorType>FLAVOR_WONDER</FlavorType>
			<Flavor>-25</Flavor>
		</Row>
		<Row>
			<AIMilitaryStrategyType>MILITARYAISTRATEGY_NEED_RANGED</AIMilitaryStrategyType>
			<FlavorType>FLAVOR_OFFENSE</FlavorType>
			<Flavor>-10</Flavor>
		</Row>
		<Row>
			<AIMilitaryStrategyType>MILITARYAISTRATEGY_NEED_RANGED</AIMilitaryStrategyType>
			<FlavorType>FLAVOR_DEFENSE</FlavorType>
			<Flavor>-10</Flavor>
		</Row>
		<Row>
			<AIMilitaryStrategyType>MILITARYAISTRATEGY_NEED_RANGED</AIMilitaryStrategyType>
			<FlavorType>FLAVOR_RANGED</FlavorType>
			<Flavor>75</Flavor>
		</Row>
		<Row>
			<AIMilitaryStrategyType>MILITARYAISTRATEGY_ENOUGH_RANGED</AIMilitaryStrategyType>
			<FlavorType>FLAVOR_OFFENSE</FlavorType>
			<Flavor>5</Flavor>
		</Row>
		<Row>
			<AIMilitaryStrategyType>MILITARYAISTRATEGY_ENOUGH_RANGED</AIMilitaryStrategyType>
			<FlavorType>FLAVOR_DEFENSE</FlavorType>
			<Flavor>5</Flavor>
		</Row>
		<Row>
			<AIMilitaryStrategyType>MILITARYAISTRATEGY_ENOUGH_RANGED</AIMilitaryStrategyType>
			<FlavorType>FLAVOR_RANGED</FlavorType>
			<Flavor>-50</Flavor>
		</Row>
		<Row>
			<AIMilitaryStrategyType>MILITARYAISTRATEGY_NEED_MOBILE</AIMilitaryStrategyType>
			<FlavorType>FLAVOR_MOBILE</FlavorType>
			<Flavor>75</Flavor>
		</Row>
		<Row>
			<AIMilitaryStrategyType>MILITARYAISTRATEGY_ENOUGH_MOBILE</AIMilitaryStrategyType>
			<FlavorType>FLAVOR_MOBILE</FlavorType>
			<Flavor>-50</Flavor>
		</Row>
		<Row>
			<AIMilitaryStrategyType>MILITARYAISTRATEGY_NEED_AIR</AIMilitaryStrategyType>
			<FlavorType>FLAVOR_AIR</FlavorType>
			<Flavor>150</Flavor>
		</Row>
		<Row>
			<AIMilitaryStrategyType>MILITARYAISTRATEGY_NEED_NUKE</AIMilitaryStrategyType>
			<FlavorType>FLAVOR_NUKE</FlavorType>
			<Flavor>200</Flavor>
		</Row>
		<Row>
			<AIMilitaryStrategyType>MILITARYAISTRATEGY_ENOUGH_AIR</AIMilitaryStrategyType>
			<FlavorType>FLAVOR_AIR</FlavorType>
			<Flavor>-50</Flavor>
		</Row>
		<Row>
			<AIMilitaryStrategyType>MILITARYAISTRATEGY_NEED_ANTIAIR</AIMilitaryStrategyType>
			<FlavorType>FLAVOR_ANTIAIR</FlavorType>
			<Flavor>75</Flavor>
		</Row>
		<Row>
			<AIMilitaryStrategyType>MILITARYAISTRATEGY_ENOUGH_ANTIAIR</AIMilitaryStrategyType>
			<FlavorType>FLAVOR_ANTIAIR</FlavorType>
			<Flavor>-100</Flavor>
		</Row>
	</AIMilitaryStrategy_Flavors>
	<AIMilitaryStrategy_PersonalityFlavorThresholdMods>
		<Row>
			<AIMilitaryStrategyType>MILITARYAISTRATEGY_ERADICATE_BARBARIANS</AIMilitaryStrategyType>
			<FlavorType>FLAVOR_OFFENSE</FlavorType>
			<Flavor>-2</Flavor>
		</Row>
		<Row>
			<AIMilitaryStrategyType>MILITARYAISTRATEGY_ERADICATE_BARBARIANS</AIMilitaryStrategyType>
			<FlavorType>FLAVOR_DEFENSE</FlavorType>
			<Flavor>2</Flavor>
		</Row>
	</AIMilitaryStrategy_PersonalityFlavorThresholdMods>
</GameData>
